<?xml version="1.0" encoding="UTF-8"?>
<beans xmlns="http://www.springframework.org/schema/beans" 
    xmlns:xsi="http://www.w3.org/2001/XMLSchema-instance"
    xmlns:mvc="http://www.springframework.org/schema/mvc"
    xmlns:p="http://www.springframework.org/schema/p" 
	xmlns:jee="http://www.springframework.org/schema/jee"
    xmlns:context="http://www.springframework.org/schema/context"
    xsi:schemaLocation="
        http://www.springframework.org/schema/jee http://www.springframework.org/schema/jee/spring-jee-3.0.xsd
        http://www.springframework.org/schema/beans http://www.springframework.org/schema/beans/spring-beans.xsd
        http://www.springframework.org/schema/context http://www.springframework.org/schema/context/spring-context.xsd
        http://www.springframework.org/schema/mvc http://www.springframework.org/schema/mvc/spring-mvc.xsd
">

    <mvc:annotation-driven />

	<jee:jndi-lookup id="tweetRepository" jndi-name="osgi:service/org.opennms.twissandra.api.TweetRepository" />
	
    <bean class="org.opennms.twissandra.webapp.internal.TweetsController">
    	<property name="tweetRepository" ref="tweetRepository" />
    </bean>

    <bean id="tilesConfigurer" class="org.springframework.web.servlet.view.tiles2.TilesConfigurer">
        <property name="definitions">
            <list>
                <value>/WEB-INF/tiles-definitions.xml</value>
            </list>
        </property>
    </bean>

    <bean id="viewResolver" class="org.springframework.web.servlet.view.UrlBasedViewResolver">
        <property name="viewClass" value="org.springframework.web.servlet.view.tiles2.TilesView"/>
    </bean>

<!-- 
   <bean id="jstlViewResolver" class="org.springframework.web.servlet.view.UrlBasedViewResolver" p:order="1">
      <property name="viewClass" value="org.springframework.web.servlet.view.JstlView"/>
      <property name="prefix" value="/WEB-INF/jsp/"/>
      <property name="suffix" value=".jsp"/>
    </bean>
 -->
</beans>
